CYB600_Lab1/__init__.py
CYB600_Lab1/app.py
CYB600_Lab1_Huff4-0.1.dist-info/LICENSE
CYB600_Lab1_Huff4-0.1.dist-info/METADATA
CYB600_Lab1_Huff4-0.1.dist-info/WHEEL
CYB600_Lab1_Huff4-0.1.dist-info/entry_points.txt
CYB600_Lab1_Huff4-0.1.dist-info/top_level.txt
CYB600_Lab1_Huff4-0.1.dist-info/RECORD
